sel_suod/__init__.py
sel_suod/version.py
sel_suod/models/__init__.py
sel_suod/models/base.py
sel_suod/models/cost_predictor.py
sel_suod/models/jl_projection.py
sel_suod/models/parallel_processes.py
sel_suod/models/sub_projection.py
sel_suod/models/saved_models/__init__.py
sel_suod/test/__init__.py
sel_suod/test/test_base.py
sel_suod/test/test_cost_predictor.py
sel_suod/test/test_model_save_load.py
sel_suod/test/test_utility.py
sel_suod/utils/__init__.py
sel_suod/utils/utility.py
sel_suod-0.1.dist-info/LICENSE
sel_suod-0.1.dist-info/METADATA
sel_suod-0.1.dist-info/WHEEL
sel_suod-0.1.dist-info/top_level.txt
sel_suod-0.1.dist-info/RECORD
