Metadata-Version: 2.1
Name: sel_suod
Version: 0.1
Summary: Fork from SUOD v0.1.3 (by Yue Zhao)
Home-page: https://github.com/jcribeiro98/Selectable_SUOD
Download-URL: https://github.com/jcribeiro98/Selectable_SUOD/archive/refs/heads/master.zip
Author: Jose Cribeiro
Author-email: jose@cribeiro.de
Keywords: ensemble learning,anomaly detection,outlier ensembles,data mining,machine learning,python
Classifier: Development Status :: 5 - Production/Stable
Classifier: Intended Audience :: Education
Classifier: Intended Audience :: Financial and Insurance Industry
Classifier: Intended Audience :: Science/Research
Classifier: Intended Audience :: Developers
Classifier: Intended Audience :: Information Technology
Classifier: License :: OSI Approved :: BSD License
Classifier: Programming Language :: Python :: 3.5
Classifier: Programming Language :: Python :: 3.6
Classifier: Programming Language :: Python :: 3.7
License-File: LICENSE
Requires-Dist: combo
Requires-Dist: joblib >=0.14.1
Requires-Dist: matplotlib
Requires-Dist: numpy >=1.13
Requires-Dist: scipy >=0.19.1
Requires-Dist: scikit-learn >=1.0
Requires-Dist: pandas
Requires-Dist: psutil
Requires-Dist: pyod >=1.0
